bot_storage/storage.py
bot_storage-1.0.1.dist-info/LICENSE
bot_storage-1.0.1.dist-info/METADATA
bot_storage-1.0.1.dist-info/WHEEL
bot_storage-1.0.1.dist-info/top_level.txt
bot_storage-1.0.1.dist-info/RECORD
