Metadata-Version: 2.1
Name: bot-storage
Version: 1.0.1
Summary: Storage for bots that allows you to save the states and data of users.
Home-page: https://github.com/IvanRomanchenko/bot-storage
Author: Daniil Marchenko, Ivan Romanchenko
Author-email: vanvanych789@gmail.com
License: UNKNOWN
Platform: UNKNOWN
Classifier: Programming Language :: Python :: 3.10
Classifier: License :: OSI Approved :: MIT License
Classifier: Operating System :: OS Independent
Requires-Python: >=3.6
License-File: LICENSE
Requires-Dist: redis (==4.1.4)
Requires-Dist: ujson (==5.1.0)
